setup.cfg
setup.py
eubh_local.egg-info/PKG-INFO
eubh_local.egg-info/SOURCES.txt
eubh_local.egg-info/dependency_links.txt
eubh_local.egg-info/entry_points.txt
eubh_local.egg-info/requires.txt
eubh_local.egg-info/top_level.txt
eubh_local.egg-info/zip-safe
src/__init__.py
src/__main__.py
src/api.py
src/config.py
src/container.py
src/get.py
src/init.py
src/put.py
src/status.py
src/utils.py
src/watch.py